topdesk/__init__.py
topdesk/errors.py
topdesk/topdesk.py
topdesk-0.0.17.dist-info/LICENSE
topdesk-0.0.17.dist-info/METADATA
topdesk-0.0.17.dist-info/WHEEL
topdesk-0.0.17.dist-info/top_level.txt
topdesk-0.0.17.dist-info/RECORD
