Metadata-Version: 2.1
Name: topdesk
Version: 0.0.17
Summary: A modern TOPdesk wrapper for Python
Home-page: https://gitlab.com/wobcom/topdesk
Author: Veit Heller
License: GPLv3
License-File: LICENSE
Requires-Dist: requests (>=2.22.0)
